bs_roformer/__init__.py
bs_roformer/attend.py
bs_roformer/bs_roformer.py
bs_roformer/mel_band_roformer.py
bs_roformer-1.1.0.dist-info/licenses/LICENSE
bs_roformer-1.1.0.dist-info/METADATA
bs_roformer-1.1.0.dist-info/WHEEL
bs_roformer-1.1.0.dist-info/top_level.txt
bs_roformer-1.1.0.dist-info/RECORD
