Metadata-Version: 2.4
Name: BS-RoFormer
Version: 1.1.0
Summary: BS-RoFormer - Band-Split Rotary Transformer for SOTA Music Source Separation
Home-page: https://github.com/lucidrains/BS-RoFormer
Author: Phil Wang
Author-email: lucidrains@gmail.com
License: MIT
Keywords: artificial intelligence,deep learning,transformers,attention mechanism,music source separation
Classifier: Development Status :: 4 - Beta
Classifier: Intended Audience :: Developers
Classifier: Topic :: Scientific/Engineering :: Artificial Intelligence
Classifier: License :: OSI Approved :: MIT License
Classifier: Programming Language :: Python :: 3.6
License-File: LICENSE
Requires-Dist: beartype
Requires-Dist: einops>=0.8.0
Requires-Dist: hyper-connections>=0.4.4
Requires-Dist: librosa
Requires-Dist: PoPE-pytorch>=0.0.15
Requires-Dist: rotary-embedding-torch>=0.3.6
Requires-Dist: torch>=2.0
Dynamic: author
Dynamic: author-email
Dynamic: classifier
Dynamic: description-content-type
Dynamic: home-page
Dynamic: keywords
Dynamic: license
Dynamic: license-file
Dynamic: requires-dist
Dynamic: summary
